[
  {
    "text": "Virtual Staging",
    "href": "/virtual-staging",
    "visible": true
  },
  {
    "text": "Photo Editing",
    "href": "/photo-editing",
    "visible": true
  },
  {
    "text": "Renovation",
    "href": "/home-renovation",
    "visible": true
  },
  {
    "text": "B2B Solution",
    "href": "/b2b",
    "visible": true
  },
  {
    "text": "Pricing",
    "href": "https://app.aihomedesign.com/pricing",
    "visible": true
  },
  {
    "text": "Get started for free",
    "href": "https://app.aihomedesign.com/",
    "visible": true
  },
  {
    "text": "Start decluttering free",
    "href": "https://app.aihomedesign.com/generate/?tool_slug=tool-item-removal",
    "visible": true
  },
  {
    "text": "Get Started",
    "href": "https://app.aihomedesign.com/generate/?tool_slug=tool-item-removal",
    "visible": true
  },
  {
    "text": "01         Upload photos  Upload a property photo to get started.",
    "href": null,
    "visible": true
  },
  {
    "text": "02         AI analyzes photos  AI detects clutter, furniture, and other unwanted",
    "href": null,
    "visible": true
  },
  {
    "text": "03         Select removal type  Choose whole-room declutter or select & remove s",
    "href": null,
    "visible": true
  },
  {
    "text": "04         Generate and edit results  Create cleaned-up results, regenerate vari",
    "href": null,
    "visible": true
  },
  {
    "text": "05         Download results  Save the final photos and move them into your listi",
    "href": null,
    "visible": true
  },
  {
    "text": "aihomedesign.com",
    "href": "https://aihomedesign.com",
    "visible": true
  },
  {
    "text": "Brokerages",
    "href": null,
    "visible": true
  },
  {
    "text": "MLSs",
    "href": null,
    "visible": true
  },
  {
    "text": "Service Partners",
    "href": null,
    "visible": true
  },
  {
    "text": "Book a Demo",
    "href": "https://calendly.com/aihomedesign/30min",
    "visible": true
  },
  {
    "text": "Explore Solutions",
    "href": "/b2b",
    "visible": true
  },
  {
    "text": "Explore our blog",
    "href": "/blog",
    "visible": true
  },
  {
    "text": "AI Item Removal for Real Estate: How It Works + Best Tools  AI real estate item ",
    "href": "/blog/services/best-ai-item-remover-2",
    "visible": true
  },
  {
    "text": "Real Estate Photo Editing Workflow: What Comes First  Build a smarter real estat",
    "href": "/blog/services/real-estate-photo-editing-workflow-image-enhancement-item-removal-or-virtual-staging-first",
    "visible": true
  },
  {
    "text": "Top 5 AI Photo Editor Online Tools for Real Estate (2026 Guide)  Compare the top",
    "href": "/blog/real-estate-photography/ai-photo-editor-online-real-estate",
    "visible": true
  },
  {
    "text": "Start Your First Listing",
    "href": "https://app.aihomedesign.com/generate/?tool_slug=tool-item-removal",
    "visible": true
  },
  {
    "text": "View More",
    "href": null,
    "visible": true
  }
]